slurpit/__init__.py
slurpit/api.py
slurpit/apis/__init__.py
slurpit/apis/baseapi.py
slurpit/apis/deviceapi.py
slurpit/apis/planningapi.py
slurpit/apis/platformapi.py
slurpit/apis/scannerapi.py
slurpit/apis/scraperapi.py
slurpit/apis/templateapi.py
slurpit/apis/userapi.py
slurpit/apis/vaultapi.py
slurpit/models/__init__.py
slurpit/models/basemodel.py
slurpit/models/device.py
slurpit/models/planning.py
slurpit/models/platform.py
slurpit/models/scanner.py
slurpit/models/template.py
slurpit/models/user.py
slurpit/models/vault.py
slurpkit-0.9.19.dist-info/LICENSE
slurpkit-0.9.19.dist-info/METADATA
slurpkit-0.9.19.dist-info/WHEEL
slurpkit-0.9.19.dist-info/RECORD
