Metadata-Version: 2.1
Name: slurpkit
Version: 0.9.19
Summary: A robust Python SDK for slurpit
Author: Slurp'it
Author-email: info@slurpit.io
Requires-Python: >=3.10,<4.0
Classifier: Programming Language :: Python :: 3
Classifier: Programming Language :: Python :: 3.10
Classifier: Programming Language :: Python :: 3.11
Classifier: Programming Language :: Python :: 3.12
Requires-Dist: pandas (>=2.2.2,<3.0.0)
Requires-Dist: requests (>=2.31.0,<3.0.0)
